primelib/__init__.py
primelib/prime_numbers.py
timenet2300-0.0.1.dist-info/LICENSE
timenet2300-0.0.1.dist-info/METADATA
timenet2300-0.0.1.dist-info/WHEEL
timenet2300-0.0.1.dist-info/top_level.txt
timenet2300-0.0.1.dist-info/RECORD
